ppt_mcp_server.py
slide_layout_templates.json
tools/__init__.py
tools/chart_tools.py
tools/connector_tools.py
tools/content_tools.py
tools/hyperlink_tools.py
tools/master_tools.py
tools/presentation_tools.py
tools/professional_tools.py
tools/structural_tools.py
tools/template_tools.py
tools/transition_tools.py
utils/__init__.py
utils/content_utils.py
utils/core_utils.py
utils/design_utils.py
utils/presentation_utils.py
utils/template_utils.py
utils/validation_utils.py
office_powerpoint_mcp_server_fastmcp-2.0.7.dist-info/METADATA
office_powerpoint_mcp_server_fastmcp-2.0.7.dist-info/WHEEL
office_powerpoint_mcp_server_fastmcp-2.0.7.dist-info/entry_points.txt
office_powerpoint_mcp_server_fastmcp-2.0.7.dist-info/licenses/LICENSE
office_powerpoint_mcp_server_fastmcp-2.0.7.dist-info/RECORD
