Metadata-Version: 2.4
Name: office-powerpoint-mcp-server-fastmcp
Version: 2.0.7
Summary: MCP Server for PowerPoint manipulation using python-pptx - Consolidated Edition
Project-URL: Homepage, https://github.com/fastmcp-me/office-powerpoint-mcp-server#readme
Project-URL: Repository, https://github.com/fastmcp-me/office-powerpoint-mcp-server.git
Project-URL: Issues, https://github.com/fastmcp-me/office-powerpoint-mcp-server/issues
Author-email: GongRzhe <gongrzhe@gmail.com>
License: MIT License
License-File: LICENSE
Classifier: License :: OSI Approved :: MIT License
Classifier: Operating System :: OS Independent
Classifier: Programming Language :: Python :: 3
Requires-Python: >=3.6
Requires-Dist: fonttools>=4.0.0
Requires-Dist: mcp[cli]>=1.3.0
Requires-Dist: pillow>=8.0.0
Requires-Dist: python-pptx>=0.6.21
